{
  "$schema": "https://developer.microsoft.com/json-schemas/fabric/item/report/definition/visualContainer/1.6.0/schema.json",
  "name": "d8e45ab025305510ec0d",
  "position": {
    "x": 973.33333333333337,
    "y": 280,
    "z": 41000,
    "height": 110,
    "width": 480,
    "tabOrder": 41000
  },
  "visual": {
    "visualType": "textbox",
    "objects": {
      "general": [
        {
          "properties": {
            "paragraphs": [
              {
                "textRuns": [
                  {
                    "value": "CURRENT EMPLOYEES",
                    "textStyle": {
                      "fontWeight": "bold",
                      "fontSize": "24pt"
                    }
                  }
                ]
              }
            ]
          }
        }
      ]
    },
    "visualContainerObjects": {
      "background": [
        {
          "properties": {
            "show": {
              "expr": {
                "Literal": {
                  "Value": "false"
                }
              }
            }
          }
        }
      ]
    },
    "drillFilterOtherVisuals": true
  }
}